adafruit_rplidar.py
adafruit_rplidar-0.0.1.dist-info/LICENSE
adafruit_rplidar-0.0.1.dist-info/METADATA
adafruit_rplidar-0.0.1.dist-info/WHEEL
adafruit_rplidar-0.0.1.dist-info/top_level.txt
adafruit_rplidar-0.0.1.dist-info/RECORD
