Metadata-Version: 2.1
Name: adafruit-rplidar
Version: 0.0.1
Summary: Slamtec RPLIDAR A1 interface
Home-page: https://github.com/adafruit/Adafruit_CircuitPython_RPLIDAR
Author: Dave Astels
Author-email: dastels@daveastels.com
License: UNKNOWN
Platform: UNKNOWN
Classifier: Programming Language :: Python :: 3
Classifier: License :: OSI Approved :: MIT License
Classifier: Operating System :: OS Independent
